Metadata-Version: 2.1
Name: square_artkov
Version: 1.0.0
Summary: Square function
Author-email: Artem Kovalenkor <artkov@ttu.ee>
License-File: LICENSE
Classifier: License :: OSI Approved :: MIT License
Classifier: Operating System :: OS Independent
Classifier: Programming Language :: Python :: 3
Requires-Python: >=3.7
